MANIFEST.in
README.rst
setup.py
errorcats/__init__.py
errorcats/error.py
errorcats.egg-info/PKG-INFO
errorcats.egg-info/SOURCES.txt
errorcats.egg-info/dependency_links.txt
errorcats.egg-info/top_level.txt
errorcats/templates/__init__.py
errorcats/templates/error.mak