Metadata-Version: 1.0
Name: errorcats
Version: 1.0.2
Summary: An amusing replacement error handler
Home-page: https://github.com/Qalthos/errorcats
Author: Nathaniel Case
Author-email: Qalthos@gmail.com
License: UNKNOWN
Platform: UNKNOWN
